.distriploy.yml
.gitignore
LICENSE
README.rst
setup.py
distriploy/__init__.py
distriploy/__main__.py
distriploy/distriploy.py
distriploy/git.py
distriploy/github.py
distriploy/mirror_academictorrents.py
distriploy/mirror_osf.py
distriploy/mirror_rsync.py
distriploy/osf.py
distriploy/release_github.py
distriploy.egg-info/PKG-INFO
distriploy.egg-info/SOURCES.txt
distriploy.egg-info/dependency_links.txt
distriploy.egg-info/entry_points.txt
distriploy.egg-info/not-zip-safe
distriploy.egg-info/requires.txt
distriploy.egg-info/top_level.txt