Metadata-Version: 2.1
Name: distriploy
Version: 0.16
Summary: Release deployment utility
Home-page: https://github.com/exmakhina/distriploy
Author: Jérôme Carretero
Author-email: cJ-py-spam@zougloub.eu
License: MIT
Keywords: releng,deployment,distribution
Platform: UNKNOWN
Classifier: Development Status :: 4 - Beta
Classifier: Environment :: Console
Classifier: Intended Audience :: Developers
Classifier: Natural Language :: English
Classifier: License :: OSI Approved :: MIT License
Classifier: Operating System :: Unix
Classifier: Operating System :: MacOS
Classifier: Programming Language :: Python :: 3 :: Only
Classifier: Programming Language :: Python :: 3
Classifier: Programming Language :: Python :: 3.6
Classifier: Programming Language :: Python :: 3.7
Classifier: Programming Language :: Python :: 3.8
Classifier: Programming Language :: Python :: Implementation :: CPython
Classifier: Programming Language :: Python :: Implementation :: PyPy
Classifier: Programming Language :: Python
Classifier: Topic :: Software Development
Requires-Python: >=3.6
Provides-Extra: osf
